{"matchId":"07bafb7d-8fba-4b0d-be1b-013aef163354.nakama-0","mapId":"AmbroseValley","date":"2026-02-13","startTime":1770983903000,"endTime":1770984446000,"durationSeconds":543,"players":[{"playerId":"c830d8d5-e7c2-4d09-935e-d3c79c5903a1","isBot":false,"label":"Human c830d8","firstT":0,"lastT":543,"points":[{"t":0,"x":-172.4,"z":335.7,"mx":224.8,"my":103.8},{"t":10,"x":-172.5,"z":334.9,"mx":224.7,"my":104.8},{"t":15,"x":-157.1,"z":314.1,"mx":242.3,"my":128.4},{"t":20,"x":-152.5,"z":310.5,"mx":247.4,"my":132.6},{"t":25,"x":-153,"z":302.8,"mx":247,"my":141.3},{"t":30,"x":-160.6,"z":296.6,"mx":238.2,"my":148.4},{"t":35,"x":-152.5,"z":292.5,"mx":247.5,"my":153},{"t":40,"x":-138.8,"z":280.6,"mx":263.1,"my":166.6},{"t":45,"x":-124.7,"z":255.7,"mx":279.1,"my":194.9},{"t":50,"x":-131.4,"z":267.2,"mx":271.5,"my":181.8},{"t":55,"x":-115.3,"z":238.6,"mx":289.7,"my":214.4},{"t":60,"x":-97.1,"z":214.5,"mx":310.5,"my":241.8},{"t":65,"x":-80.2,"z":205.3,"mx":329.8,"my":252.3},{"t":70,"x":-56.8,"z":215.8,"mx":356.4,"my":240.2},{"t":75,"x":-38.8,"z":221.3,"mx":376.9,"my":234.1},{"t":80,"x":-20.1,"z":225.3,"mx":398.2,"my":229.5},{"t":86,"x":6.1,"z":225.6,"mx":427.9,"my":229.2},{"t":91,"x":27.6,"z":234.3,"mx":452.4,"my":219.3},{"t":101,"x":33,"z":236.9,"mx":458.5,"my":216.3},{"t":106,"x":35,"z":245.5,"mx":460.8,"my":206.5},{"t":111,"x":26.9,"z":232.6,"mx":451.5,"my":221.2},{"t":116,"x":26.5,"z":225.3,"mx":451.1,"my":229.5},{"t":121,"x":36.5,"z":235.2,"mx":462.6,"my":218.2},{"t":126,"x":37.4,"z":226,"mx":463.5,"my":228.7},{"t":136,"x":44.2,"z":230.3,"mx":471.2,"my":223.8},{"t":141,"x":42.9,"z":224.5,"mx":469.8,"my":230.4},{"t":146,"x":48.7,"z":244.2,"mx":476.4,"my":208},{"t":151,"x":40,"z":231.5,"mx":466.4,"my":222.4},{"t":156,"x":43.2,"z":235.3,"mx":470.2,"my":218.1},{"t":161,"x":35.7,"z":237.6,"mx":461.6,"my":215.5},{"t":166,"x":37,"z":227.7,"mx":463.1,"my":226.7},{"t":176,"x":39.6,"z":220.8,"mx":466.1,"my":234.6},{"t":181,"x":54.1,"z":203.2,"mx":482.5,"my":254.6},{"t":186,"x":45.8,"z":194,"mx":473.1,"my":265.1},{"t":191,"x":37.4,"z":189.3,"mx":463.5,"my":270.5},{"t":196,"x":37,"z":170.7,"mx":463.1,"my":291.6},{"t":201,"x":46.6,"z":143.3,"mx":474,"my":322.7},{"t":206,"x":28.8,"z":129.1,"mx":453.8,"my":339},{"t":211,"x":14,"z":145.1,"mx":436.9,"my":320.8},{"t":216,"x":3.6,"z":151.9,"mx":425.1,"my":313.1},{"t":221,"x":2.3,"z":123.7,"mx":423.6,"my":345},{"t":226,"x":14.3,"z":101.6,"mx":437.3,"my":370.2},{"t":231,"x":19.8,"z":93.4,"mx":443.6,"my":379.5},{"t":236,"x":18.8,"z":83.9,"mx":442.4,"my":390.4},{"t":241,"x":8.5,"z":72.3,"mx":430.6,"my":403.6},{"t":246,"x":9.8,"z":65.5,"mx":432.2,"my":411.3},{"t":251,"x":-10.7,"z":23.2,"mx":408.8,"my":459.4},{"t":256,"x":-5.7,"z":33.9,"mx":414.5,"my":447.2},{"t":261,"x":-28.1,"z":7.8,"mx":389,"my":477},{"t":267,"x":-37.6,"z":0.4,"mx":378.2,"my":485.4},{"t":272,"x":-25.3,"z":-15.6,"mx":392.2,"my":503.6},{"t":282,"x":-28.6,"z":-24.9,"mx":388.5,"my":514.2},{"t":287,"x":-30.8,"z":-32.1,"mx":386,"my":522.4},{"t":292,"x":-27.8,"z":-40,"mx":389.3,"my":531.4},{"t":297,"x":-26.1,"z":-38.1,"mx":391.3,"my":529.1},{"t":312,"x":-29.8,"z":-41.2,"mx":387.1,"my":532.7},{"t":317,"x":-30.8,"z":-49.3,"mx":385.9,"my":542},{"t":327,"x":-28.3,"z":-52,"mx":388.8,"my":545},{"t":332,"x":-21.3,"z":-56.8,"mx":396.8,"my":550.4},{"t":337,"x":-16.4,"z":-53.1,"mx":402.3,"my":546.3},{"t":342,"x":-10.4,"z":-45.3,"mx":409.2,"my":537.4},{"t":347,"x":-12.9,"z":-54.1,"mx":406.3,"my":547.3},{"t":352,"x":-2.4,"z":-70.1,"mx":418.2,"my":565.6},{"t":357,"x":-1.7,"z":-80.1,"mx":419,"my":576.9},{"t":377,"x":-2.6,"z":-78.3,"mx":418.1,"my":574.9},{"t":382,"x":-2.7,"z":-64.1,"mx":417.9,"my":558.7},{"t":387,"x":11.1,"z":-37.3,"mx":433.6,"my":528.3},{"t":392,"x":32.8,"z":-25.6,"mx":458.3,"my":515},{"t":397,"x":32,"z":-19.8,"mx":457.4,"my":508.4},{"t":402,"x":27.6,"z":-22.6,"mx":452.4,"my":511.6},{"t":407,"x":27.6,"z":-35.2,"mx":452.4,"my":525.9},{"t":417,"x":26.2,"z":-34.8,"mx":450.7,"my":525.5},{"t":427,"x":30.3,"z":-34.7,"mx":455.5,"my":525.3},{"t":432,"x":46,"z":-37.7,"mx":473.3,"my":528.7},{"t":437,"x":41.2,"z":-45.8,"mx":467.8,"my":538},{"t":443,"x":43.9,"z":-42.6,"mx":470.9,"my":534.4},{"t":448,"x":34.3,"z":-46.8,"mx":460,"my":539.1},{"t":453,"x":29.5,"z":-61.9,"mx":454.6,"my":556.2},{"t":458,"x":39.6,"z":-84.2,"mx":466.1,"my":581.6},{"t":463,"x":42,"z":-94.5,"mx":468.8,"my":593.3},{"t":468,"x":46,"z":-94.9,"mx":473.4,"my":593.8},{"t":473,"x":55.2,"z":-92.5,"mx":483.7,"my":591.1},{"t":483,"x":59.7,"z":-95.6,"mx":488.9,"my":594.6},{"t":488,"x":68.1,"z":-91.3,"mx":498.4,"my":589.7},{"t":493,"x":72.4,"z":-80.4,"mx":503.3,"my":577.3},{"t":498,"x":79.4,"z":-54.7,"mx":511.3,"my":548.1},{"t":503,"x":80.4,"z":-53.9,"mx":512.4,"my":547.1},{"t":508,"x":79,"z":-55.3,"mx":510.9,"my":548.8},{"t":513,"x":79.8,"z":-53.9,"mx":511.8,"my":547.1},{"t":518,"x":95.7,"z":-49.1,"mx":529.9,"my":541.7},{"t":523,"x":120.7,"z":-42.4,"mx":558.4,"my":534.1},{"t":528,"x":149.6,"z":-44.1,"mx":591.2,"my":536.1},{"t":533,"x":164.1,"z":-48.6,"mx":607.6,"my":541.2},{"t":538,"x":189.3,"z":-59.9,"mx":636.4,"my":554},{"t":543,"x":196.8,"z":-68.3,"mx":644.9,"my":563.5}]}],"events":[{"id":"e0","event":"Loot","category":"loot","t":18,"x":-150.5,"z":314.5,"mx":249.7,"my":128,"playerId":"c830d8d5-e7c2-4d09-935e-d3c79c5903a1","isBot":false},{"id":"e1","event":"Loot","category":"loot","t":24,"x":-152.9,"z":302.8,"mx":247.1,"my":141.3,"playerId":"c830d8d5-e7c2-4d09-935e-d3c79c5903a1","isBot":false},{"id":"e2","event":"Loot","category":"loot","t":24,"x":-152.9,"z":302.8,"mx":247.1,"my":141.3,"playerId":"c830d8d5-e7c2-4d09-935e-d3c79c5903a1","isBot":false},{"id":"e3","event":"Loot","category":"loot","t":31,"x":-160.6,"z":296.6,"mx":238.2,"my":148.4,"playerId":"c830d8d5-e7c2-4d09-935e-d3c79c5903a1","isBot":false},{"id":"e4","event":"Loot","category":"loot","t":32,"x":-160.6,"z":296.6,"mx":238.2,"my":148.4,"playerId":"c830d8d5-e7c2-4d09-935e-d3c79c5903a1","isBot":false},{"id":"e5","event":"Loot","category":"loot","t":37,"x":-144.8,"z":294.5,"mx":256.3,"my":150.7,"playerId":"c830d8d5-e7c2-4d09-935e-d3c79c5903a1","isBot":false},{"id":"e6","event":"BotKill","category":"kill","t":95,"x":28.5,"z":232.4,"mx":453.5,"my":221.4,"playerId":"c830d8d5-e7c2-4d09-935e-d3c79c5903a1","isBot":false},{"id":"e7","event":"Loot","category":"loot","t":103,"x":31.6,"z":241.9,"mx":456.9,"my":210.6,"playerId":"c830d8d5-e7c2-4d09-935e-d3c79c5903a1","isBot":false},{"id":"e8","event":"Loot","category":"loot","t":104,"x":33.5,"z":243.5,"mx":459.1,"my":208.8,"playerId":"c830d8d5-e7c2-4d09-935e-d3c79c5903a1","isBot":false},{"id":"e9","event":"Loot","category":"loot","t":105,"x":33.5,"z":243.5,"mx":459.1,"my":208.8,"playerId":"c830d8d5-e7c2-4d09-935e-d3c79c5903a1","isBot":false},{"id":"e10","event":"Loot","category":"loot","t":122,"x":42.7,"z":234.7,"mx":469.5,"my":218.8,"playerId":"c830d8d5-e7c2-4d09-935e-d3c79c5903a1","isBot":false},{"id":"e11","event":"Loot","category":"loot","t":127,"x":37.4,"z":226,"mx":463.5,"my":228.7,"playerId":"c830d8d5-e7c2-4d09-935e-d3c79c5903a1","isBot":false},{"id":"e12","event":"Loot","category":"loot","t":137,"x":44.2,"z":230.3,"mx":471.2,"my":223.8,"playerId":"c830d8d5-e7c2-4d09-935e-d3c79c5903a1","isBot":false},{"id":"e13","event":"Loot","category":"loot","t":141,"x":42.9,"z":224.5,"mx":469.8,"my":230.4,"playerId":"c830d8d5-e7c2-4d09-935e-d3c79c5903a1","isBot":false},{"id":"e14","event":"Loot","category":"loot","t":147,"x":48.7,"z":244.2,"mx":476.4,"my":208,"playerId":"c830d8d5-e7c2-4d09-935e-d3c79c5903a1","isBot":false},{"id":"e15","event":"Loot","category":"loot","t":159,"x":34.3,"z":240.5,"mx":460,"my":212.2,"playerId":"c830d8d5-e7c2-4d09-935e-d3c79c5903a1","isBot":false},{"id":"e16","event":"Loot","category":"loot","t":165,"x":36.7,"z":225.6,"mx":462.7,"my":229.2,"playerId":"c830d8d5-e7c2-4d09-935e-d3c79c5903a1","isBot":false},{"id":"e17","event":"Loot","category":"loot","t":167,"x":35.8,"z":226.7,"mx":461.7,"my":227.9,"playerId":"c830d8d5-e7c2-4d09-935e-d3c79c5903a1","isBot":false},{"id":"e18","event":"Loot","category":"loot","t":191,"x":37.4,"z":189.3,"mx":463.5,"my":270.5,"playerId":"c830d8d5-e7c2-4d09-935e-d3c79c5903a1","isBot":false},{"id":"e19","event":"Loot","category":"loot","t":215,"x":8,"z":153.6,"mx":430.1,"my":311,"playerId":"c830d8d5-e7c2-4d09-935e-d3c79c5903a1","isBot":false},{"id":"e20","event":"Loot","category":"loot","t":229,"x":17.4,"z":95.3,"mx":440.8,"my":377.5,"playerId":"c830d8d5-e7c2-4d09-935e-d3c79c5903a1","isBot":false},{"id":"e21","event":"Loot","category":"loot","t":233,"x":19.8,"z":93.4,"mx":443.6,"my":379.5,"playerId":"c830d8d5-e7c2-4d09-935e-d3c79c5903a1","isBot":false},{"id":"e22","event":"BotKill","category":"kill","t":264,"x":-36.1,"z":6.4,"mx":379.9,"my":478.6,"playerId":"c830d8d5-e7c2-4d09-935e-d3c79c5903a1","isBot":false},{"id":"e23","event":"Loot","category":"loot","t":268,"x":-36,"z":-5.1,"mx":380,"my":491.6,"playerId":"c830d8d5-e7c2-4d09-935e-d3c79c5903a1","isBot":false},{"id":"e24","event":"Loot","category":"loot","t":269,"x":-36,"z":-5.1,"mx":380,"my":491.6,"playerId":"c830d8d5-e7c2-4d09-935e-d3c79c5903a1","isBot":false},{"id":"e25","event":"Loot","category":"loot","t":278,"x":-28.7,"z":-17.6,"mx":388.3,"my":505.9,"playerId":"c830d8d5-e7c2-4d09-935e-d3c79c5903a1","isBot":false},{"id":"e26","event":"Loot","category":"loot","t":311,"x":-27.6,"z":-40,"mx":389.6,"my":531.3,"playerId":"c830d8d5-e7c2-4d09-935e-d3c79c5903a1","isBot":false},{"id":"e27","event":"BotKill","category":"kill","t":320,"x":-30.5,"z":-45.7,"mx":386.3,"my":537.8,"playerId":"c830d8d5-e7c2-4d09-935e-d3c79c5903a1","isBot":false},{"id":"e28","event":"BotKill","category":"kill","t":323,"x":-31,"z":-46.6,"mx":385.7,"my":538.9,"playerId":"c830d8d5-e7c2-4d09-935e-d3c79c5903a1","isBot":false},{"id":"e29","event":"Loot","category":"loot","t":349,"x":-7.5,"z":-63.1,"mx":412.4,"my":557.6,"playerId":"c830d8d5-e7c2-4d09-935e-d3c79c5903a1","isBot":false},{"id":"e30","event":"Loot","category":"loot","t":350,"x":-7.5,"z":-63.1,"mx":412.4,"my":557.6,"playerId":"c830d8d5-e7c2-4d09-935e-d3c79c5903a1","isBot":false},{"id":"e31","event":"Loot","category":"loot","t":355,"x":-1.7,"z":-80.1,"mx":419,"my":576.9,"playerId":"c830d8d5-e7c2-4d09-935e-d3c79c5903a1","isBot":false},{"id":"e32","event":"Loot","category":"loot","t":355,"x":-1.7,"z":-80.1,"mx":419,"my":576.9,"playerId":"c830d8d5-e7c2-4d09-935e-d3c79c5903a1","isBot":false},{"id":"e33","event":"Loot","category":"loot","t":356,"x":-1.7,"z":-80.1,"mx":419,"my":576.9,"playerId":"c830d8d5-e7c2-4d09-935e-d3c79c5903a1","isBot":false},{"id":"e34","event":"Loot","category":"loot","t":357,"x":-1.7,"z":-80.1,"mx":419,"my":576.9,"playerId":"c830d8d5-e7c2-4d09-935e-d3c79c5903a1","isBot":false},{"id":"e35","event":"BotKill","category":"kill","t":362,"x":-1.4,"z":-82.4,"mx":419.4,"my":579.6,"playerId":"c830d8d5-e7c2-4d09-935e-d3c79c5903a1","isBot":false},{"id":"e36","event":"BotKill","category":"kill","t":371,"x":-0.4,"z":-83.8,"mx":420.5,"my":581.2,"playerId":"c830d8d5-e7c2-4d09-935e-d3c79c5903a1","isBot":false},{"id":"e37","event":"Loot","category":"loot","t":378,"x":-2.9,"z":-75.3,"mx":417.6,"my":571.5,"playerId":"c830d8d5-e7c2-4d09-935e-d3c79c5903a1","isBot":false},{"id":"e38","event":"Loot","category":"loot","t":380,"x":-2.1,"z":-68.2,"mx":418.5,"my":563.4,"playerId":"c830d8d5-e7c2-4d09-935e-d3c79c5903a1","isBot":false},{"id":"e39","event":"Loot","category":"loot","t":394,"x":31,"z":-29,"mx":456.2,"my":518.8,"playerId":"c830d8d5-e7c2-4d09-935e-d3c79c5903a1","isBot":false},{"id":"e40","event":"Loot","category":"loot","t":413,"x":27.6,"z":-35.2,"mx":452.4,"my":525.9,"playerId":"c830d8d5-e7c2-4d09-935e-d3c79c5903a1","isBot":false},{"id":"e41","event":"Loot","category":"loot","t":415,"x":27.6,"z":-35.2,"mx":452.4,"my":525.9,"playerId":"c830d8d5-e7c2-4d09-935e-d3c79c5903a1","isBot":false},{"id":"e42","event":"Loot","category":"loot","t":420,"x":26,"z":-34.8,"mx":450.5,"my":525.4,"playerId":"c830d8d5-e7c2-4d09-935e-d3c79c5903a1","isBot":false},{"id":"e43","event":"BotKill","category":"kill","t":476,"x":57.4,"z":-94.4,"mx":486.3,"my":593.2,"playerId":"c830d8d5-e7c2-4d09-935e-d3c79c5903a1","isBot":false},{"id":"e44","event":"BotKill","category":"kill","t":481,"x":59.7,"z":-95.6,"mx":488.9,"my":594.6,"playerId":"c830d8d5-e7c2-4d09-935e-d3c79c5903a1","isBot":false},{"id":"e45","event":"BotKill","category":"kill","t":483,"x":59.7,"z":-95.6,"mx":488.9,"my":594.6,"playerId":"c830d8d5-e7c2-4d09-935e-d3c79c5903a1","isBot":false},{"id":"e46","event":"BotKill","category":"kill","t":500,"x":79.2,"z":-55.3,"mx":511.1,"my":548.8,"playerId":"c830d8d5-e7c2-4d09-935e-d3c79c5903a1","isBot":false},{"id":"e47","event":"Loot","category":"loot","t":503,"x":80.4,"z":-53.9,"mx":512.4,"my":547.1,"playerId":"c830d8d5-e7c2-4d09-935e-d3c79c5903a1","isBot":false},{"id":"e48","event":"Loot","category":"loot","t":504,"x":80.5,"z":-53.2,"mx":512.5,"my":546.4,"playerId":"c830d8d5-e7c2-4d09-935e-d3c79c5903a1","isBot":false},{"id":"e49","event":"Loot","category":"loot","t":506,"x":81.2,"z":-52.4,"mx":513.3,"my":545.5,"playerId":"c830d8d5-e7c2-4d09-935e-d3c79c5903a1","isBot":false},{"id":"e50","event":"Loot","category":"loot","t":516,"x":95.2,"z":-51.6,"mx":529.3,"my":544.6,"playerId":"c830d8d5-e7c2-4d09-935e-d3c79c5903a1","isBot":false},{"id":"e51","event":"Loot","category":"loot","t":517,"x":94.8,"z":-51.2,"mx":528.8,"my":544.1,"playerId":"c830d8d5-e7c2-4d09-935e-d3c79c5903a1","isBot":false}]}