{"matchId":"573343fd-a200-4d12-a0e6-c1517bc186a4.nakama-0","mapId":"AmbroseValley","date":"2026-02-10","startTime":1770764621000,"endTime":1770765024000,"durationSeconds":403,"players":[{"playerId":"193d0736-f731-4a57-97c6-b0cf71b47ecb","isBot":false,"label":"Human 193d07","firstT":0,"lastT":403,"points":[{"t":0,"x":268.1,"z":-47.6,"mx":726,"my":540},{"t":20,"x":264.3,"z":-48.6,"mx":721.7,"my":541.2},{"t":25,"x":243.3,"z":-57.8,"mx":697.9,"my":551.6},{"t":30,"x":234.6,"z":-71.6,"mx":687.9,"my":567.3},{"t":35,"x":218.8,"z":-95.7,"mx":670,"my":594.7},{"t":40,"x":223,"z":-109.1,"mx":674.7,"my":610},{"t":45,"x":222.9,"z":-131.6,"mx":674.6,"my":635.6},{"t":51,"x":225,"z":-155.1,"mx":677,"my":662.3},{"t":56,"x":211.4,"z":-167.3,"mx":661.5,"my":676.1},{"t":61,"x":184,"z":-173.2,"mx":630.4,"my":682.8},{"t":66,"x":183.6,"z":-204.1,"mx":629.9,"my":718.1},{"t":71,"x":186,"z":-225.4,"mx":632.6,"my":742.2},{"t":76,"x":194.1,"z":-240.5,"mx":641.8,"my":759.4},{"t":81,"x":186.7,"z":-243.6,"mx":633.4,"my":763},{"t":86,"x":188.6,"z":-247.4,"mx":635.6,"my":767.3},{"t":91,"x":193,"z":-248.1,"mx":640.5,"my":768.1},{"t":96,"x":192.8,"z":-250.4,"mx":640.3,"my":770.7},{"t":101,"x":188.7,"z":-254.8,"mx":635.6,"my":775.8},{"t":106,"x":197,"z":-248.5,"mx":645.1,"my":768.6},{"t":111,"x":195.8,"z":-252.8,"mx":643.8,"my":773.5},{"t":126,"x":197.4,"z":-258.4,"mx":645.6,"my":779.8},{"t":131,"x":191.2,"z":-256.9,"mx":638.6,"my":778.1},{"t":136,"x":191,"z":-260.4,"mx":638.2,"my":782.1},{"t":141,"x":181.9,"z":-281.6,"mx":628,"my":806.3},{"t":146,"x":178.6,"z":-286.8,"mx":624.2,"my":812.2},{"t":151,"x":178.6,"z":-293.3,"mx":624.2,"my":819.6},{"t":161,"x":174,"z":-284.7,"mx":619,"my":809.8},{"t":166,"x":174.7,"z":-292.6,"mx":619.8,"my":818.7},{"t":171,"x":174.4,"z":-295,"mx":619.4,"my":821.5},{"t":176,"x":175.8,"z":-300.1,"mx":621,"my":827.3},{"t":181,"x":168.8,"z":-296.4,"mx":613,"my":823},{"t":186,"x":165.8,"z":-288.9,"mx":609.6,"my":814.5},{"t":191,"x":166,"z":-294.3,"mx":609.8,"my":820.7},{"t":196,"x":174.8,"z":-293.8,"mx":619.8,"my":820.1},{"t":201,"x":165,"z":-298.7,"mx":608.8,"my":825.6},{"t":206,"x":163.1,"z":-297.1,"mx":606.6,"my":823.9},{"t":211,"x":152.7,"z":-291.5,"mx":594.7,"my":817.5},{"t":216,"x":149.1,"z":-308.8,"mx":590.7,"my":837.2},{"t":221,"x":153.1,"z":-312.7,"mx":595.2,"my":841.6},{"t":226,"x":147.4,"z":-323.1,"mx":588.7,"my":853.4},{"t":232,"x":150.7,"z":-320,"mx":592.4,"my":849.9},{"t":237,"x":149.5,"z":-318.7,"mx":591.1,"my":848.4},{"t":242,"x":139.6,"z":-324.3,"mx":579.8,"my":854.8},{"t":247,"x":146.3,"z":-339.7,"mx":587.5,"my":872.4},{"t":252,"x":138.6,"z":-332.6,"mx":578.6,"my":864.2},{"t":257,"x":136,"z":-335.6,"mx":575.7,"my":867.7},{"t":267,"x":147.7,"z":-350.8,"mx":589,"my":884.9},{"t":277,"x":149.8,"z":-349.2,"mx":591.4,"my":883.1},{"t":282,"x":140.7,"z":-344.5,"mx":581.1,"my":877.7},{"t":287,"x":140.8,"z":-354.2,"mx":581.2,"my":888.8},{"t":292,"x":138.5,"z":-356.7,"mx":578.6,"my":891.7},{"t":297,"x":142.8,"z":-350.4,"mx":583.5,"my":884.5},{"t":302,"x":135.4,"z":-351.5,"mx":575.1,"my":885.7},{"t":307,"x":138.8,"z":-345,"mx":578.9,"my":878.3},{"t":312,"x":141,"z":-336.5,"mx":581.4,"my":868.7},{"t":317,"x":135.4,"z":-324.7,"mx":575.1,"my":855.3},{"t":322,"x":129.5,"z":-297.2,"mx":568.3,"my":824},{"t":327,"x":105,"z":-289.1,"mx":540.5,"my":814.8},{"t":332,"x":101.9,"z":-281.8,"mx":536.9,"my":806.5},{"t":337,"x":95.9,"z":-271.9,"mx":530.1,"my":795.2},{"t":342,"x":91.8,"z":-271.5,"mx":525.4,"my":794.7},{"t":352,"x":99.8,"z":-279.7,"mx":534.5,"my":804},{"t":357,"x":103.2,"z":-271.2,"mx":538.4,"my":794.3},{"t":362,"x":106.9,"z":-265.5,"mx":542.6,"my":788},{"t":367,"x":104,"z":-270.9,"mx":539.3,"my":794.1},{"t":377,"x":98,"z":-273.9,"mx":532.5,"my":797.5},{"t":387,"x":100.3,"z":-269.7,"mx":535.1,"my":792.7},{"t":392,"x":89.8,"z":-264.4,"mx":523.1,"my":786.7},{"t":397,"x":94.4,"z":-260.7,"mx":528.4,"my":782.5},{"t":403,"x":98,"z":-263.4,"mx":532.5,"my":785.5}]}],"events":[{"id":"e0","event":"Loot","category":"loot","t":90,"x":193,"z":-248.1,"mx":640.5,"my":768.1,"playerId":"193d0736-f731-4a57-97c6-b0cf71b47ecb","isBot":false},{"id":"e1","event":"Loot","category":"loot","t":90,"x":193,"z":-248.1,"mx":640.5,"my":768.1,"playerId":"193d0736-f731-4a57-97c6-b0cf71b47ecb","isBot":false},{"id":"e2","event":"Loot","category":"loot","t":126,"x":197.4,"z":-258.4,"mx":645.6,"my":779.8,"playerId":"193d0736-f731-4a57-97c6-b0cf71b47ecb","isBot":false},{"id":"e3","event":"Loot","category":"loot","t":126,"x":197.4,"z":-258.4,"mx":645.6,"my":779.8,"playerId":"193d0736-f731-4a57-97c6-b0cf71b47ecb","isBot":false},{"id":"e4","event":"Loot","category":"loot","t":173,"x":174.4,"z":-295,"mx":619.4,"my":821.5,"playerId":"193d0736-f731-4a57-97c6-b0cf71b47ecb","isBot":false},{"id":"e5","event":"Loot","category":"loot","t":180,"x":168.5,"z":-296.7,"mx":612.7,"my":823.4,"playerId":"193d0736-f731-4a57-97c6-b0cf71b47ecb","isBot":false},{"id":"e6","event":"Loot","category":"loot","t":185,"x":165.8,"z":-288.9,"mx":609.6,"my":814.5,"playerId":"193d0736-f731-4a57-97c6-b0cf71b47ecb","isBot":false},{"id":"e7","event":"Loot","category":"loot","t":185,"x":165.8,"z":-288.9,"mx":609.6,"my":814.5,"playerId":"193d0736-f731-4a57-97c6-b0cf71b47ecb","isBot":false},{"id":"e8","event":"Loot","category":"loot","t":204,"x":163.7,"z":-297.1,"mx":607.3,"my":823.9,"playerId":"193d0736-f731-4a57-97c6-b0cf71b47ecb","isBot":false},{"id":"e9","event":"Loot","category":"loot","t":218,"x":149.1,"z":-308.8,"mx":590.7,"my":837.2,"playerId":"193d0736-f731-4a57-97c6-b0cf71b47ecb","isBot":false},{"id":"e10","event":"Loot","category":"loot","t":253,"x":138.6,"z":-332.6,"mx":578.6,"my":864.2,"playerId":"193d0736-f731-4a57-97c6-b0cf71b47ecb","isBot":false},{"id":"e11","event":"Loot","category":"loot","t":256,"x":136,"z":-335.6,"mx":575.7,"my":867.7,"playerId":"193d0736-f731-4a57-97c6-b0cf71b47ecb","isBot":false},{"id":"e12","event":"Loot","category":"loot","t":262,"x":138.2,"z":-338.9,"mx":578.2,"my":871.5,"playerId":"193d0736-f731-4a57-97c6-b0cf71b47ecb","isBot":false},{"id":"e13","event":"Loot","category":"loot","t":269,"x":147.7,"z":-350.7,"mx":589.1,"my":884.8,"playerId":"193d0736-f731-4a57-97c6-b0cf71b47ecb","isBot":false},{"id":"e14","event":"Loot","category":"loot","t":271,"x":148.2,"z":-351.7,"mx":589.6,"my":886,"playerId":"193d0736-f731-4a57-97c6-b0cf71b47ecb","isBot":false},{"id":"e15","event":"Loot","category":"loot","t":274,"x":149,"z":-351.1,"mx":590.5,"my":885.3,"playerId":"193d0736-f731-4a57-97c6-b0cf71b47ecb","isBot":false},{"id":"e16","event":"Loot","category":"loot","t":274,"x":149,"z":-351.1,"mx":590.5,"my":885.3,"playerId":"193d0736-f731-4a57-97c6-b0cf71b47ecb","isBot":false},{"id":"e17","event":"Loot","category":"loot","t":291,"x":138.5,"z":-356.7,"mx":578.6,"my":891.7,"playerId":"193d0736-f731-4a57-97c6-b0cf71b47ecb","isBot":false},{"id":"e18","event":"Loot","category":"loot","t":337,"x":95.9,"z":-271.9,"mx":530.1,"my":795.2,"playerId":"193d0736-f731-4a57-97c6-b0cf71b47ecb","isBot":false},{"id":"e19","event":"Loot","category":"loot","t":344,"x":91.3,"z":-270.5,"mx":524.9,"my":793.5,"playerId":"193d0736-f731-4a57-97c6-b0cf71b47ecb","isBot":false},{"id":"e20","event":"BotKilled","category":"death","t":401,"x":97.9,"z":-263.3,"mx":532.4,"my":785.5,"playerId":"193d0736-f731-4a57-97c6-b0cf71b47ecb","isBot":false}]}