{"matchId":"5918bc12-a3c2-43d4-a529-5c8ae62c9d2f.nakama-0","mapId":"AmbroseValley","date":"2026-02-11","startTime":1770770966000,"endTime":1770771215000,"durationSeconds":249,"players":[{"playerId":"af1c46f4-49d9-45f3-85e7-8290f9a55cc1","isBot":false,"label":"Human af1c46","firstT":0,"lastT":156,"points":[{"t":0,"x":-313.9,"z":0.1,"mx":63.9,"my":485.7},{"t":15,"x":-299.1,"z":11.7,"mx":80.7,"my":472.5},{"t":20,"x":-291.1,"z":22.9,"mx":89.8,"my":459.8},{"t":25,"x":-285.6,"z":36.5,"mx":96,"my":444.3},{"t":30,"x":-278.9,"z":50.8,"mx":103.7,"my":428},{"t":36,"x":-268.1,"z":63.8,"mx":115.9,"my":413.3},{"t":41,"x":-255.5,"z":65.7,"mx":130.3,"my":411.1},{"t":46,"x":-241.6,"z":67.7,"mx":146,"my":408.8},{"t":51,"x":-227.9,"z":69.7,"mx":161.7,"my":406.5},{"t":61,"x":-213.6,"z":68,"mx":177.9,"my":408.5},{"t":71,"x":-199.4,"z":67.9,"mx":194.1,"my":408.6},{"t":76,"x":-179.5,"z":68.2,"mx":216.7,"my":408.2},{"t":81,"x":-167.5,"z":58.5,"mx":230.4,"my":419.3},{"t":86,"x":-147.3,"z":55.9,"mx":253.4,"my":422.3},{"t":91,"x":-132.3,"z":59.5,"mx":270.5,"my":418.2},{"t":96,"x":-121,"z":54,"mx":283.3,"my":424.4},{"t":101,"x":-119.8,"z":54.1,"mx":284.7,"my":424.3},{"t":106,"x":-120.8,"z":54,"mx":283.6,"my":424.4},{"t":111,"x":-121.6,"z":58.8,"mx":282.6,"my":419},{"t":116,"x":-107.7,"z":49.7,"mx":298.5,"my":429.3},{"t":121,"x":-103.5,"z":30.4,"mx":303.2,"my":451.3},{"t":126,"x":-110.8,"z":16.6,"mx":294.9,"my":467},{"t":131,"x":-115.4,"z":3.3,"mx":289.7,"my":482.1},{"t":136,"x":-119.5,"z":6.7,"mx":285,"my":478.2},{"t":141,"x":-115.8,"z":2.8,"mx":289.2,"my":482.7},{"t":151,"x":-110.9,"z":12.9,"mx":294.8,"my":471.1},{"t":156,"x":-109.2,"z":21.1,"mx":296.7,"my":461.8}]},{"playerId":"1440","isBot":true,"label":"Bot 1440","firstT":5,"lastT":96,"points":[{"t":5,"x":245.1,"z":-46.4,"mx":699.9,"my":538.6},{"t":10,"x":224.8,"z":-45.7,"mx":676.8,"my":537.9},{"t":15,"x":220.4,"z":-30.4,"mx":671.8,"my":520.4},{"t":20,"x":210.3,"z":-13.5,"mx":660.2,"my":501.2},{"t":25,"x":193.7,"z":-26.9,"mx":641.4,"my":516.4},{"t":30,"x":178.6,"z":-31.3,"mx":624.2,"my":521.4},{"t":36,"x":168.7,"z":-37.6,"mx":612.9,"my":528.6},{"t":41,"x":169.3,"z":-49.5,"mx":613.6,"my":542.1},{"t":46,"x":150.3,"z":-43.7,"mx":592,"my":535.5},{"t":51,"x":130,"z":-36.9,"mx":568.9,"my":527.9},{"t":56,"x":118,"z":-34.7,"mx":555.2,"my":525.4},{"t":61,"x":124.3,"z":-41,"mx":562.4,"my":532.5},{"t":66,"x":119.5,"z":-35.8,"mx":556.9,"my":526.5},{"t":71,"x":116.6,"z":-31.6,"mx":553.7,"my":521.7},{"t":76,"x":109,"z":-33.7,"mx":545,"my":524.2},{"t":81,"x":97.5,"z":-40.4,"mx":531.9,"my":531.8},{"t":91,"x":100.5,"z":-49.4,"mx":535.4,"my":542.1},{"t":96,"x":99.2,"z":-58.1,"mx":533.9,"my":552}]},{"playerId":"1444","isBot":true,"label":"Bot 1444","firstT":5,"lastT":141,"points":[{"t":5,"x":-290.4,"z":-332.3,"mx":90.6,"my":863.9},{"t":10,"x":-273.9,"z":-315,"mx":109.3,"my":844.3},{"t":15,"x":-261.8,"z":-299.7,"mx":123.2,"my":826.9},{"t":20,"x":-246.4,"z":-286,"mx":140.6,"my":811.3},{"t":25,"x":-232,"z":-273,"mx":157.1,"my":796.5},{"t":30,"x":-226,"z":-265.2,"mx":163.8,"my":787.6},{"t":36,"x":-219.9,"z":-260.5,"mx":170.8,"my":782.2},{"t":41,"x":-214.4,"z":-269.4,"mx":177,"my":792.3},{"t":46,"x":-224.3,"z":-278.3,"mx":165.8,"my":802.5},{"t":51,"x":-246.1,"z":-287.3,"mx":140.9,"my":812.7},{"t":56,"x":-257.9,"z":-306.8,"mx":127.5,"my":834.9},{"t":61,"x":-260,"z":-324.3,"mx":125.1,"my":854.9},{"t":66,"x":-237.6,"z":-333.6,"mx":150.6,"my":865.4},{"t":71,"x":-219.2,"z":-337.1,"mx":171.5,"my":869.4},{"t":76,"x":-226.3,"z":-335.2,"mx":163.5,"my":867.2},{"t":81,"x":-218.3,"z":-329.1,"mx":172.6,"my":860.3},{"t":86,"x":-219,"z":-336.2,"mx":171.9,"my":868.3},{"t":91,"x":-218.4,"z":-354.5,"mx":172.4,"my":889.2},{"t":96,"x":-208.1,"z":-376.8,"mx":184.3,"my":914.6},{"t":101,"x":-192.5,"z":-380,"mx":202,"my":918.2},{"t":106,"x":-187.5,"z":-357.7,"mx":207.7,"my":892.8},{"t":111,"x":-166.1,"z":-345.4,"mx":232,"my":878.8},{"t":116,"x":-162.2,"z":-327.3,"mx":236.4,"my":858.2},{"t":121,"x":-163.7,"z":-324.6,"mx":234.7,"my":855.1},{"t":126,"x":-168.9,"z":-329.5,"mx":228.8,"my":860.7},{"t":131,"x":-173,"z":-334.2,"mx":224.1,"my":866},{"t":136,"x":-183.3,"z":-324.7,"mx":212.5,"my":855.3},{"t":141,"x":-182,"z":-306.5,"mx":213.9,"my":834.6}]},{"playerId":"1448","isBot":true,"label":"Bot 1448","firstT":5,"lastT":247,"points":[{"t":5,"x":217.2,"z":211.3,"mx":668.1,"my":245.4},{"t":10,"x":214.5,"z":200.3,"mx":665.1,"my":257.9},{"t":15,"x":226.6,"z":178.9,"mx":678.8,"my":282.3},{"t":20,"x":218.6,"z":161.6,"mx":669.7,"my":302},{"t":25,"x":198.1,"z":148.1,"mx":646.3,"my":317.3},{"t":30,"x":193.3,"z":146.5,"mx":640.9,"my":319.2},{"t":36,"x":194.8,"z":171.1,"mx":642.6,"my":291.2},{"t":41,"x":194.5,"z":178.9,"mx":642.2,"my":282.3},{"t":46,"x":190.5,"z":155,"mx":637.7,"my":309.5},{"t":51,"x":186,"z":142.2,"mx":632.6,"my":324.1},{"t":56,"x":178.2,"z":165.4,"mx":623.7,"my":297.6},{"t":61,"x":177.2,"z":182.7,"mx":622.6,"my":278},{"t":66,"x":170.2,"z":159.3,"mx":614.6,"my":304.5},{"t":71,"x":166.5,"z":137.1,"mx":610.4,"my":329.8},{"t":76,"x":164.8,"z":112.8,"mx":608.5,"my":357.5},{"t":81,"x":163.1,"z":90.7,"mx":606.6,"my":382.7},{"t":86,"x":177.2,"z":86.5,"mx":622.6,"my":387.4},{"t":91,"x":186.7,"z":81.1,"mx":633.4,"my":393.5},{"t":101,"x":179.6,"z":101.3,"mx":625.3,"my":370.6},{"t":106,"x":163.7,"z":89.3,"mx":607.2,"my":384.2},{"t":116,"x":174.6,"z":87.7,"mx":619.6,"my":386},{"t":121,"x":156.7,"z":79.8,"mx":599.3,"my":395},{"t":126,"x":141.4,"z":69.6,"mx":581.9,"my":406.6},{"t":131,"x":135.3,"z":62.5,"mx":574.9,"my":414.7},{"t":136,"x":123.9,"z":54.8,"mx":562,"my":423.5},{"t":141,"x":126,"z":51.9,"mx":564.3,"my":426.7},{"t":146,"x":114.1,"z":62.7,"mx":550.8,"my":414.5},{"t":151,"x":120.7,"z":62.7,"mx":558.3,"my":414.4},{"t":156,"x":117.8,"z":54.8,"mx":555,"my":423.5},{"t":161,"x":98.4,"z":40.3,"mx":533,"my":440},{"t":166,"x":78.7,"z":39.5,"mx":510.6,"my":440.9},{"t":171,"x":55.9,"z":42.4,"mx":484.6,"my":437.6},{"t":176,"x":31.7,"z":37.6,"mx":457.1,"my":443.1},{"t":181,"x":7.7,"z":32.7,"mx":429.8,"my":448.6},{"t":186,"x":4.3,"z":19.8,"mx":425.9,"my":463.3},{"t":191,"x":9.1,"z":13,"mx":431.4,"my":471},{"t":196,"x":2.9,"z":5.4,"mx":424.3,"my":479.7},{"t":201,"x":1.9,"z":-13.4,"mx":423.1,"my":501.1},{"t":206,"x":1.8,"z":-28.7,"mx":423,"my":518.4},{"t":212,"x":4.4,"z":-14.7,"mx":425.9,"my":502.5},{"t":217,"x":1.2,"z":-3.9,"mx":422.4,"my":490.2},{"t":222,"x":-1.2,"z":20.3,"mx":419.6,"my":462.8},{"t":227,"x":-15.2,"z":31.7,"mx":403.7,"my":449.7},{"t":232,"x":-31.6,"z":40.8,"mx":385,"my":439.4},{"t":237,"x":-44.3,"z":20.5,"mx":370.5,"my":462.5},{"t":242,"x":-54.4,"z":6.9,"mx":359.1,"my":477.9},{"t":247,"x":-68,"z":3.5,"mx":343.6,"my":481.8}]},{"playerId":"1452","isBot":true,"label":"Bot 1452","firstT":5,"lastT":237,"points":[{"t":5,"x":-115.7,"z":-349.9,"mx":289.3,"my":884},{"t":10,"x":-135.2,"z":-338.9,"mx":267.1,"my":871.4},{"t":15,"x":-154.3,"z":-323.3,"mx":245.5,"my":853.6},{"t":20,"x":-161.5,"z":-305.7,"mx":237.2,"my":833.6},{"t":25,"x":-159.3,"z":-281.9,"mx":239.7,"my":806.6},{"t":30,"x":-175.2,"z":-269.1,"mx":221.6,"my":792},{"t":36,"x":-181.6,"z":-268,"mx":214.3,"my":790.8},{"t":41,"x":-169.8,"z":-270.3,"mx":227.8,"my":793.3},{"t":46,"x":-158.8,"z":-287.7,"mx":240.2,"my":813.1},{"t":51,"x":-166.3,"z":-273.5,"mx":231.8,"my":797},{"t":56,"x":-189,"z":-267.8,"mx":206,"my":790.5},{"t":61,"x":-212.6,"z":-266.8,"mx":179.1,"my":789.4},{"t":66,"x":-230,"z":-266.4,"mx":159.3,"my":788.9},{"t":71,"x":-239.2,"z":-275.5,"mx":148.8,"my":799.3},{"t":76,"x":-254.6,"z":-293.7,"mx":131.3,"my":820},{"t":81,"x":-246.6,"z":-292.9,"mx":140.5,"my":819.1},{"t":86,"x":-224.2,"z":-282.5,"mx":165.9,"my":807.3},{"t":91,"x":-209.3,"z":-265.8,"mx":182.8,"my":788.2},{"t":96,"x":-206.7,"z":-250.1,"mx":185.7,"my":770.4},{"t":101,"x":-200.5,"z":-236.6,"mx":192.8,"my":755},{"t":106,"x":-188.1,"z":-215.4,"mx":207,"my":731},{"t":111,"x":-175.4,"z":-197,"mx":221.4,"my":710},{"t":116,"x":-157.7,"z":-180.7,"mx":241.6,"my":691.4},{"t":121,"x":-145.5,"z":-170.3,"mx":255.4,"my":679.5},{"t":126,"x":-145.7,"z":-192.1,"mx":255.2,"my":704.4},{"t":131,"x":-155.2,"z":-206.3,"mx":244.4,"my":720.6},{"t":136,"x":-142.9,"z":-187.3,"mx":258.3,"my":699},{"t":141,"x":-144.4,"z":-169.7,"mx":256.6,"my":679},{"t":146,"x":-131.5,"z":-151.6,"mx":271.3,"my":658.3},{"t":151,"x":-117,"z":-138.5,"mx":287.9,"my":643.4},{"t":156,"x":-105.6,"z":-131.7,"mx":300.8,"my":635.7},{"t":161,"x":-122.4,"z":-138.7,"mx":281.7,"my":643.7},{"t":166,"x":-128.2,"z":-158.6,"mx":275.1,"my":666.3},{"t":171,"x":-113.2,"z":-160.1,"mx":292.2,"my":668},{"t":176,"x":-100.1,"z":-139.3,"mx":307,"my":644.3},{"t":181,"x":-93.6,"z":-122.7,"mx":314.5,"my":625.4},{"t":186,"x":-88.4,"z":-109.6,"mx":320.4,"my":610.6},{"t":191,"x":-83.2,"z":-96.5,"mx":326.3,"my":595.7},{"t":196,"x":-76.9,"z":-83.3,"mx":333.5,"my":580.6},{"t":201,"x":-58.3,"z":-77.8,"mx":354.6,"my":574.4},{"t":206,"x":-61.4,"z":-79.6,"mx":351.2,"my":576.4},{"t":212,"x":-53.6,"z":-68.7,"mx":360,"my":564.1},{"t":217,"x":-55.4,"z":-81.2,"mx":357.9,"my":578.2},{"t":222,"x":-48.1,"z":-92.9,"mx":366.2,"my":591.5},{"t":227,"x":-38.7,"z":-83.5,"mx":377,"my":580.9},{"t":232,"x":-42.4,"z":-77.5,"mx":372.7,"my":574},{"t":237,"x":-46.8,"z":-75.2,"mx":367.7,"my":571.4}]},{"playerId":"1456","isBot":true,"label":"Bot 1456","firstT":5,"lastT":237,"points":[{"t":5,"x":-159.3,"z":321.4,"mx":239.8,"my":120.1},{"t":10,"x":-155,"z":300.7,"mx":244.7,"my":143.7},{"t":15,"x":-146.8,"z":284.4,"mx":253.9,"my":162.2},{"t":20,"x":-144.4,"z":284.3,"mx":256.7,"my":162.4},{"t":25,"x":-167.4,"z":293.2,"mx":230.6,"my":152.2},{"t":30,"x":-168.7,"z":298.8,"mx":229,"my":145.8},{"t":36,"x":-155.4,"z":300,"mx":244.2,"my":144.5},{"t":41,"x":-171.2,"z":299.4,"mx":226.2,"my":145.2},{"t":46,"x":-186.2,"z":287.4,"mx":209.1,"my":158.8},{"t":51,"x":-184,"z":282.4,"mx":211.6,"my":164.5},{"t":56,"x":-174.3,"z":301,"mx":222.7,"my":143.4},{"t":61,"x":-162.5,"z":313.6,"mx":236.1,"my":129},{"t":66,"x":-180.4,"z":299.8,"mx":215.7,"my":144.7},{"t":71,"x":-165.3,"z":299,"mx":232.9,"my":145.7},{"t":76,"x":-184.6,"z":290.6,"mx":211,"my":155.2},{"t":81,"x":-186.4,"z":271.3,"mx":208.9,"my":177.1},{"t":86,"x":-188.3,"z":281,"mx":206.7,"my":166.2},{"t":91,"x":-174.8,"z":300.5,"mx":222.1,"my":144},{"t":96,"x":-184.5,"z":290.3,"mx":211,"my":155.5},{"t":101,"x":-186.5,"z":271.6,"mx":208.8,"my":176.8},{"t":106,"x":-190.7,"z":249.2,"mx":204,"my":202.3},{"t":111,"x":-189.9,"z":226.4,"mx":204.9,"my":228.2},{"t":116,"x":-180.7,"z":229.8,"mx":215.4,"my":224.3},{"t":121,"x":-179.9,"z":205.7,"mx":216.3,"my":251.8},{"t":126,"x":-178.2,"z":192.6,"mx":218.3,"my":266.7},{"t":131,"x":-167.3,"z":190.3,"mx":230.6,"my":269.3},{"t":136,"x":-170.1,"z":171.2,"mx":227.4,"my":291.1},{"t":141,"x":-175.1,"z":151.7,"mx":221.7,"my":313.3},{"t":146,"x":-183.9,"z":133.6,"mx":211.7,"my":333.8},{"t":151,"x":-182.5,"z":111.5,"mx":213.3,"my":358.9},{"t":156,"x":-172.4,"z":89.2,"mx":224.9,"my":384.4},{"t":161,"x":-157.4,"z":72.4,"mx":241.9,"my":403.5},{"t":166,"x":-145.1,"z":59.4,"mx":255.8,"my":418.2},{"t":171,"x":-137.7,"z":58.3,"mx":264.3,"my":419.4},{"t":176,"x":-130.4,"z":57.3,"mx":272.6,"my":420.6},{"t":181,"x":-125.5,"z":42.8,"mx":278.2,"my":437.1},{"t":186,"x":-121.6,"z":39.7,"mx":282.6,"my":440.7},{"t":191,"x":-121.4,"z":44.1,"mx":282.9,"my":435.7},{"t":201,"x":-113.7,"z":57.6,"mx":291.7,"my":420.3},{"t":206,"x":-106.8,"z":73.4,"mx":299.4,"my":402.3},{"t":212,"x":-105.6,"z":68.7,"mx":300.8,"my":407.6},{"t":217,"x":-116.5,"z":54.5,"mx":288.4,"my":423.8},{"t":222,"x":-119,"z":77.7,"mx":285.5,"my":397.5},{"t":227,"x":-117.5,"z":99,"mx":287.3,"my":373.2},{"t":232,"x":-106.1,"z":80,"mx":300.2,"my":394.8},{"t":237,"x":-114.8,"z":63,"mx":290.4,"my":414.1}]},{"playerId":"1460","isBot":true,"label":"Bot 1460","firstT":5,"lastT":171,"points":[{"t":5,"x":-153.2,"z":-204.3,"mx":246.7,"my":718.2},{"t":10,"x":-154.5,"z":-205.5,"mx":245.2,"my":719.7},{"t":15,"x":-144.9,"z":-185,"mx":256.1,"my":696.4},{"t":20,"x":-137.1,"z":-171.2,"mx":265,"my":680.6},{"t":25,"x":-160,"z":-170,"mx":239,"my":679.2},{"t":30,"x":-159.3,"z":-170.6,"mx":239.7,"my":680},{"t":36,"x":-135.4,"z":-172.4,"mx":266.9,"my":681.9},{"t":41,"x":-118.7,"z":-175.4,"mx":285.9,"my":685.4},{"t":46,"x":-134.5,"z":-178.9,"mx":268,"my":689.4},{"t":51,"x":-144.1,"z":-183.6,"mx":257,"my":694.7},{"t":56,"x":-145.1,"z":-160.3,"mx":255.9,"my":668.2},{"t":61,"x":-145.6,"z":-135.7,"mx":255.3,"my":640.3},{"t":66,"x":-138,"z":-113.3,"mx":263.9,"my":614.7},{"t":71,"x":-133.1,"z":-89.6,"mx":269.5,"my":587.8},{"t":76,"x":-132.1,"z":-68.5,"mx":270.6,"my":563.8},{"t":81,"x":-125.3,"z":-52,"mx":278.4,"my":545.1},{"t":86,"x":-124.6,"z":-47.2,"mx":279.2,"my":539.5},{"t":91,"x":-126.5,"z":-29,"mx":277,"my":518.8},{"t":96,"x":-127.5,"z":-13.5,"mx":276,"my":501.2},{"t":101,"x":-118.7,"z":-2.5,"mx":286,"my":488.7},{"t":106,"x":-119.4,"z":5,"mx":285.1,"my":480.2},{"t":111,"x":-135.3,"z":5.2,"mx":267.1,"my":479.9},{"t":116,"x":-120.5,"z":-2.4,"mx":283.9,"my":488.5},{"t":136,"x":-117.5,"z":-0.8,"mx":287.3,"my":486.8},{"t":141,"x":-98.1,"z":-8.4,"mx":309.3,"my":495.4},{"t":146,"x":-101.4,"z":-1,"mx":305.7,"my":487},{"t":151,"x":-100.2,"z":20.3,"mx":307,"my":462.8},{"t":156,"x":-106.5,"z":23.5,"mx":299.8,"my":459.1},{"t":161,"x":-114.2,"z":24.4,"mx":291,"my":458},{"t":166,"x":-119.6,"z":22.3,"mx":284.9,"my":460.5},{"t":171,"x":-112.9,"z":17.4,"mx":292.5,"my":466.1}]}],"events":[{"id":"e0","event":"BotKilled","category":"death","t":101,"x":97.2,"z":-77.6,"mx":531.5,"my":574.2,"playerId":"1440","isBot":true},{"id":"e1","event":"BotKill","category":"kill","t":108,"x":160.4,"z":83.9,"mx":603.4,"my":390.4,"playerId":"1448","isBot":true},{"id":"e2","event":"BotKilled","category":"death","t":141,"x":-181.5,"z":-306,"mx":214.5,"my":834,"playerId":"1444","isBot":true},{"id":"e3","event":"BotKill","category":"kill","t":150,"x":120.1,"z":63.1,"mx":557.6,"my":414,"playerId":"1448","isBot":true},{"id":"e4","event":"BotKilled","category":"death","t":155,"x":-109.2,"z":20.9,"mx":296.7,"my":462,"playerId":"af1c46f4-49d9-45f3-85e7-8290f9a55cc1","isBot":false},{"id":"e5","event":"BotKilled","category":"death","t":174,"x":-113,"z":21.9,"mx":292.5,"my":460.9,"playerId":"1460","isBot":true},{"id":"e6","event":"BotKilled","category":"death","t":237,"x":-46.9,"z":-75.4,"mx":367.7,"my":571.6,"playerId":"1452","isBot":true},{"id":"e7","event":"BotKilled","category":"death","t":239,"x":-115,"z":52.8,"mx":290.1,"my":425.7,"playerId":"1456","isBot":true},{"id":"e8","event":"BotKilled","category":"death","t":249,"x":-68.5,"z":3.4,"mx":343.1,"my":482,"playerId":"1448","isBot":true}]}