{"matchId":"80369f48-d145-4bfc-b0ee-5e805b9ec289.nakama-0","mapId":"AmbroseValley","date":"2026-02-10","startTime":1770717096000,"endTime":1770717770000,"durationSeconds":674,"players":[{"playerId":"2980f2c1-1207-428d-af58-cc62498e6dbb","isBot":false,"label":"Human 2980f2","firstT":0,"lastT":674,"points":[{"t":0,"x":267.8,"z":-48.1,"mx":725.7,"my":540.5},{"t":15,"x":264.4,"z":-48.2,"mx":721.8,"my":540.7},{"t":20,"x":246.1,"z":-54.5,"mx":700.9,"my":547.8},{"t":25,"x":231.4,"z":-72.7,"mx":684.3,"my":568.5},{"t":30,"x":207.8,"z":-83.1,"mx":657.4,"my":580.4},{"t":35,"x":186.2,"z":-82.9,"mx":632.8,"my":580.2},{"t":40,"x":193,"z":-82.1,"mx":640.6,"my":579.3},{"t":45,"x":190.8,"z":-79.4,"mx":638.1,"my":576.2},{"t":50,"x":186.3,"z":-85.3,"mx":633,"my":582.8},{"t":55,"x":166.9,"z":-84.2,"mx":610.9,"my":581.7},{"t":60,"x":158,"z":-80,"mx":600.7,"my":576.9},{"t":65,"x":158.8,"z":-74.6,"mx":601.6,"my":570.7},{"t":70,"x":153.6,"z":-74.1,"mx":595.8,"my":570.2},{"t":75,"x":151.1,"z":-78.7,"mx":592.9,"my":575.4},{"t":81,"x":146.7,"z":-76.5,"mx":587.9,"my":572.8},{"t":86,"x":148.9,"z":-70.1,"mx":590.3,"my":565.6},{"t":91,"x":139.6,"z":-71.2,"mx":579.8,"my":566.9},{"t":96,"x":147.9,"z":-90.1,"mx":589.3,"my":588.3},{"t":101,"x":155.6,"z":-91.2,"mx":598,"my":589.6},{"t":106,"x":161,"z":-116.6,"mx":604.2,"my":618.5},{"t":111,"x":175.6,"z":-138.5,"mx":620.8,"my":643.4},{"t":116,"x":197.7,"z":-150.5,"mx":645.9,"my":657},{"t":121,"x":201.7,"z":-165.5,"mx":650.4,"my":674.2},{"t":126,"x":196.1,"z":-185.1,"mx":644.1,"my":696.4},{"t":131,"x":189.3,"z":-202.1,"mx":636.4,"my":715.8},{"t":136,"x":186.5,"z":-220.4,"mx":633.1,"my":736.6},{"t":141,"x":194.9,"z":-241.4,"mx":642.8,"my":760.5},{"t":146,"x":189.2,"z":-242.8,"mx":636.3,"my":762},{"t":151,"x":187.4,"z":-246.7,"mx":634.1,"my":766.6},{"t":156,"x":192.4,"z":-255,"mx":639.9,"my":776},{"t":161,"x":199.7,"z":-254.2,"mx":648.2,"my":775},{"t":171,"x":206.8,"z":-255,"mx":656.3,"my":776},{"t":176,"x":215.3,"z":-259.3,"mx":665.9,"my":780.8},{"t":181,"x":209.6,"z":-264.4,"mx":659.4,"my":786.6},{"t":186,"x":212.5,"z":-262.6,"mx":662.8,"my":784.7},{"t":191,"x":201,"z":-274,"mx":649.7,"my":797.6},{"t":196,"x":195.6,"z":-287.8,"mx":643.6,"my":813.2},{"t":201,"x":193.5,"z":-293.5,"mx":641.1,"my":819.7},{"t":206,"x":178.1,"z":-299.2,"mx":623.6,"my":826.2},{"t":211,"x":170.4,"z":-293.4,"mx":614.8,"my":819.7},{"t":216,"x":163.4,"z":-285.4,"mx":606.9,"my":810.6},{"t":221,"x":181.5,"z":-281.3,"mx":627.5,"my":805.9},{"t":226,"x":179.1,"z":-304.1,"mx":624.8,"my":831.8},{"t":236,"x":167.6,"z":-291.8,"mx":611.7,"my":817.9},{"t":241,"x":162.8,"z":-289.5,"mx":606.2,"my":815.2},{"t":246,"x":149.5,"z":-299.3,"mx":591.1,"my":826.4},{"t":257,"x":147.8,"z":-293.5,"mx":589.1,"my":819.7},{"t":272,"x":140.3,"z":-302.2,"mx":580.6,"my":829.7},{"t":287,"x":136.1,"z":-307.7,"mx":575.8,"my":835.9},{"t":292,"x":118.5,"z":-327.8,"mx":555.7,"my":858.8},{"t":297,"x":98.7,"z":-343.3,"mx":533.3,"my":876.4},{"t":302,"x":83.8,"z":-348.9,"mx":516.4,"my":882.8},{"t":307,"x":67.8,"z":-349.8,"mx":498.1,"my":883.8},{"t":312,"x":43.1,"z":-350.2,"mx":470.1,"my":884.2},{"t":317,"x":26.2,"z":-349.2,"mx":450.8,"my":883.2},{"t":322,"x":-0.1,"z":-342.7,"mx":420.9,"my":875.8},{"t":327,"x":-27.4,"z":-337.7,"mx":389.8,"my":870.1},{"t":332,"x":-48.7,"z":-340.6,"mx":365.6,"my":873.4},{"t":337,"x":-47.7,"z":-351.1,"mx":366.7,"my":885.3},{"t":342,"x":-52.8,"z":-357.3,"mx":360.9,"my":892.4},{"t":357,"x":-52.1,"z":-354.3,"mx":361.7,"my":888.9},{"t":362,"x":-49.6,"z":-347.5,"mx":364.6,"my":881.3},{"t":367,"x":-49.9,"z":-330.3,"mx":364.2,"my":861.7},{"t":372,"x":-36.6,"z":-310.2,"mx":379.3,"my":838.8},{"t":377,"x":-14.4,"z":-299.3,"mx":404.6,"my":826.3},{"t":382,"x":-7.2,"z":-288.6,"mx":412.8,"my":814.2},{"t":387,"x":-0.1,"z":-277.8,"mx":420.9,"my":802},{"t":392,"x":-3.2,"z":-284.2,"mx":417.3,"my":809.2},{"t":397,"x":-5.2,"z":-286,"mx":415,"my":811.2},{"t":402,"x":-9.8,"z":-276.2,"mx":409.9,"my":800.1},{"t":407,"x":-15.1,"z":-282.4,"mx":403.8,"my":807.1},{"t":417,"x":-11.2,"z":-282.3,"mx":408.2,"my":807},{"t":422,"x":-2.5,"z":-285.7,"mx":418.1,"my":810.9},{"t":427,"x":-13,"z":-298,"mx":406.2,"my":824.9},{"t":433,"x":-30.4,"z":-295.4,"mx":386.3,"my":822},{"t":438,"x":-40.4,"z":-302.9,"mx":375,"my":830.4},{"t":443,"x":-38.8,"z":-282.5,"mx":376.8,"my":807.3},{"t":448,"x":-36.6,"z":-257.3,"mx":379.3,"my":778.6},{"t":453,"x":-36.7,"z":-229.4,"mx":379.3,"my":746.9},{"t":458,"x":-25.7,"z":-204.8,"mx":391.7,"my":718.8},{"t":463,"x":-14.4,"z":-195,"mx":404.6,"my":707.6},{"t":468,"x":2.5,"z":-199.3,"mx":423.9,"my":712.6},{"t":473,"x":29.5,"z":-193.3,"mx":454.5,"my":705.8},{"t":478,"x":49.8,"z":-181.4,"mx":477.6,"my":692.2},{"t":483,"x":62,"z":-171.1,"mx":491.6,"my":680.5},{"t":488,"x":68.7,"z":-163.5,"mx":499.2,"my":671.8},{"t":493,"x":63.8,"z":-142.9,"mx":493.6,"my":648.4},{"t":498,"x":62.5,"z":-149.2,"mx":492.1,"my":655.6},{"t":503,"x":68.4,"z":-170.8,"mx":498.8,"my":680.2},{"t":508,"x":89,"z":-188.6,"mx":522.2,"my":700.4},{"t":513,"x":106.9,"z":-182.3,"mx":542.7,"my":693.3},{"t":518,"x":114.6,"z":-168.9,"mx":551.4,"my":678.1},{"t":523,"x":120.5,"z":-154.3,"mx":558,"my":661.4},{"t":528,"x":122.2,"z":-148.2,"mx":560,"my":654.4},{"t":533,"x":129.8,"z":-140.2,"mx":568.7,"my":645.3},{"t":538,"x":120.6,"z":-165.8,"mx":558.2,"my":674.5},{"t":543,"x":112.6,"z":-182.5,"mx":549.1,"my":693.5},{"t":548,"x":113.6,"z":-178.2,"mx":550.3,"my":688.6},{"t":553,"x":121.9,"z":-157.3,"mx":559.6,"my":664.8},{"t":558,"x":123.5,"z":-141.5,"mx":561.5,"my":646.9},{"t":563,"x":128.4,"z":-122.8,"mx":567,"my":625.6},{"t":568,"x":132.3,"z":-104.3,"mx":571.5,"my":604.5},{"t":573,"x":140.9,"z":-106.9,"mx":581.3,"my":607.4},{"t":578,"x":157.4,"z":-93.5,"mx":600.1,"my":592.2},{"t":583,"x":169.1,"z":-68.5,"mx":613.4,"my":563.8},{"t":588,"x":173.1,"z":-46.6,"mx":617.9,"my":538.9},{"t":593,"x":180.7,"z":-32.2,"mx":626.6,"my":522.5},{"t":598,"x":186.1,"z":-26.6,"mx":632.7,"my":516.1},{"t":603,"x":174.1,"z":-24.8,"mx":619.1,"my":514},{"t":608,"x":150.4,"z":-14.8,"mx":592.1,"my":502.7},{"t":614,"x":147.3,"z":-6.9,"mx":588.6,"my":493.7},{"t":619,"x":152.9,"z":0.2,"mx":595,"my":485.6},{"t":624,"x":172.4,"z":19.7,"mx":617.1,"my":463.5},{"t":629,"x":195.8,"z":33.9,"mx":643.8,"my":447.2},{"t":634,"x":207.2,"z":58.2,"mx":656.7,"my":419.6},{"t":639,"x":213.3,"z":75.5,"mx":663.7,"my":400},{"t":644,"x":223.8,"z":99.7,"mx":675.6,"my":372.4},{"t":649,"x":230.2,"z":121.1,"mx":682.9,"my":348},{"t":654,"x":232.5,"z":139.3,"mx":685.5,"my":327.4},{"t":659,"x":231.9,"z":155.5,"mx":684.9,"my":308.9},{"t":664,"x":230.9,"z":171.4,"mx":683.7,"my":290.8},{"t":669,"x":219.4,"z":184.4,"mx":670.6,"my":276},{"t":674,"x":216.7,"z":185.5,"mx":667.5,"my":274.8}]},{"playerId":"1436","isBot":true,"label":"Bot 1436","firstT":5,"lastT":357,"points":[{"t":5,"x":-276.8,"z":-320,"mx":106,"my":849.9},{"t":10,"x":-261.2,"z":-303.4,"mx":123.8,"my":831},{"t":15,"x":-247.3,"z":-284.6,"mx":139.6,"my":809.6},{"t":20,"x":-236.2,"z":-272.9,"mx":152.3,"my":796.3},{"t":25,"x":-243.6,"z":-271.3,"mx":143.8,"my":794.6},{"t":30,"x":-245,"z":-267.4,"mx":142.3,"my":790.1},{"t":35,"x":-235.8,"z":-260.1,"mx":152.7,"my":781.8},{"t":40,"x":-220.1,"z":-242.4,"mx":170.5,"my":761.7},{"t":45,"x":-203.6,"z":-229.5,"mx":189.3,"my":746.9},{"t":50,"x":-188.3,"z":-217.6,"mx":206.7,"my":733.4},{"t":55,"x":-169.5,"z":-206.1,"mx":228.1,"my":720.3},{"t":60,"x":-186.8,"z":-214.7,"mx":208.4,"my":730.1},{"t":65,"x":-188.5,"z":-231.8,"mx":206.5,"my":749.6},{"t":70,"x":-172.6,"z":-231.5,"mx":224.6,"my":749.3},{"t":75,"x":-165,"z":-230.2,"mx":233.3,"my":747.8},{"t":81,"x":-175.9,"z":-241.4,"mx":220.8,"my":760.5},{"t":86,"x":-170.8,"z":-259.7,"mx":226.6,"my":781.3},{"t":91,"x":-165.1,"z":-250,"mx":233.1,"my":770.2},{"t":121,"x":-158.1,"z":-244.6,"mx":241,"my":764.1},{"t":126,"x":-140.4,"z":-231.8,"mx":261.2,"my":749.5},{"t":131,"x":-121.7,"z":-217,"mx":282.6,"my":732.7},{"t":136,"x":-104,"z":-199.9,"mx":302.6,"my":713.2},{"t":141,"x":-93.4,"z":-180.7,"mx":314.7,"my":691.4},{"t":146,"x":-87.6,"z":-167.2,"mx":321.3,"my":676.1},{"t":151,"x":-79.1,"z":-153.8,"mx":331,"my":660.9},{"t":156,"x":-66.9,"z":-133.4,"mx":344.9,"my":637.6},{"t":161,"x":-48.1,"z":-118.1,"mx":366.3,"my":620.3},{"t":166,"x":-29.9,"z":-103.6,"mx":386.9,"my":603.7},{"t":171,"x":-12.5,"z":-113.3,"mx":406.8,"my":614.7},{"t":176,"x":-6.7,"z":-134.1,"mx":413.3,"my":638.4},{"t":181,"x":-2.2,"z":-131.8,"mx":418.5,"my":635.8},{"t":186,"x":2.2,"z":-107.7,"mx":423.4,"my":608.3},{"t":191,"x":4.8,"z":-83.2,"mx":426.5,"my":580.5},{"t":196,"x":6.5,"z":-58.8,"mx":428.3,"my":552.7},{"t":201,"x":21.3,"z":-56.2,"mx":445.3,"my":549.7},{"t":206,"x":10.5,"z":-58.5,"mx":432.9,"my":552.4},{"t":211,"x":18.2,"z":-56.4,"mx":441.6,"my":550},{"t":216,"x":13.2,"z":-56.9,"mx":436,"my":550.6},{"t":226,"x":5.8,"z":-60,"mx":427.6,"my":554.1},{"t":231,"x":15.2,"z":-55.9,"mx":438.3,"my":549.4},{"t":241,"x":8.8,"z":-59.1,"mx":430.9,"my":553.1},{"t":246,"x":8.1,"z":-45.4,"mx":430.2,"my":537.4},{"t":251,"x":17.9,"z":-48.4,"mx":441.4,"my":540.9},{"t":257,"x":15.9,"z":-53.9,"mx":439.1,"my":547.1},{"t":262,"x":18.2,"z":-56.2,"mx":441.7,"my":549.8},{"t":267,"x":8.3,"z":-48.6,"mx":430.4,"my":541.1},{"t":272,"x":27.7,"z":-47.3,"mx":452.5,"my":539.7},{"t":277,"x":16.5,"z":-53.4,"mx":439.7,"my":546.6},{"t":282,"x":11.2,"z":-57.2,"mx":433.7,"my":550.9},{"t":287,"x":6.8,"z":-45.7,"mx":428.7,"my":537.8},{"t":292,"x":8.7,"z":-42.6,"mx":430.9,"my":534.3},{"t":297,"x":-10.2,"z":-49,"mx":409.3,"my":541.5},{"t":302,"x":-20,"z":-38.9,"mx":398.2,"my":530.1},{"t":307,"x":-14.3,"z":-16.4,"mx":404.7,"my":504.5},{"t":312,"x":-10.4,"z":-1.4,"mx":409.2,"my":487.5},{"t":317,"x":3,"z":-10.2,"mx":424.4,"my":497.4},{"t":322,"x":-8.8,"z":-6.3,"mx":410.9,"my":493},{"t":327,"x":-1.1,"z":12.4,"mx":419.7,"my":471.7},{"t":332,"x":-10.7,"z":28.7,"mx":408.8,"my":453.2},{"t":337,"x":-0.7,"z":17.8,"mx":420.2,"my":465.6},{"t":342,"x":-0.5,"z":-4.5,"mx":420.4,"my":491},{"t":347,"x":7.7,"z":-7.1,"mx":429.8,"my":493.9},{"t":352,"x":24.4,"z":-12.4,"mx":448.7,"my":499.9},{"t":357,"x":18.8,"z":-18.2,"mx":442.3,"my":506.6}]},{"playerId":"1440","isBot":true,"label":"Bot 1440","firstT":5,"lastT":101,"points":[{"t":5,"x":223.1,"z":206.4,"mx":674.8,"my":251},{"t":10,"x":213,"z":191,"mx":663.3,"my":268.6},{"t":15,"x":198.6,"z":175.4,"mx":647,"my":286.2},{"t":20,"x":183.3,"z":157.6,"mx":629.5,"my":306.5},{"t":25,"x":178,"z":147.9,"mx":623.6,"my":317.6},{"t":30,"x":157.2,"z":135.5,"mx":599.8,"my":331.7},{"t":35,"x":138.1,"z":121,"mx":578.1,"my":348.1},{"t":40,"x":122.3,"z":105.9,"mx":560.1,"my":365.3},{"t":45,"x":103.6,"z":92.6,"mx":538.9,"my":380.4},{"t":50,"x":85.6,"z":78.3,"mx":518.4,"my":396.8},{"t":55,"x":64.9,"z":70.5,"mx":494.8,"my":405.6},{"t":60,"x":44.1,"z":62.7,"mx":471.1,"my":414.5},{"t":65,"x":21,"z":54,"mx":444.9,"my":424.3},{"t":70,"x":6.8,"z":48.7,"mx":428.7,"my":430.4},{"t":75,"x":-9.3,"z":43.5,"mx":410.4,"my":436.3},{"t":81,"x":-8.5,"z":33.3,"mx":411.3,"my":447.9},{"t":86,"x":-0.8,"z":20.6,"mx":420.1,"my":462.4},{"t":91,"x":17.2,"z":5.3,"mx":440.6,"my":479.8},{"t":96,"x":3,"z":0.4,"mx":424.3,"my":485.3},{"t":101,"x":-9.4,"z":-5.2,"mx":410.2,"my":491.8}]},{"playerId":"1444","isBot":true,"label":"Bot 1444","firstT":5,"lastT":186,"points":[{"t":5,"x":-114.3,"z":-352.6,"mx":290.9,"my":887},{"t":10,"x":-132.3,"z":-339.6,"mx":270.4,"my":872.2},{"t":15,"x":-152.1,"z":-325.1,"mx":247.9,"my":855.8},{"t":20,"x":-149.1,"z":-320.9,"mx":251.3,"my":850.9},{"t":25,"x":-125.5,"z":-324.7,"mx":278.2,"my":855.3},{"t":30,"x":-120.9,"z":-324.6,"mx":283.4,"my":855.1},{"t":35,"x":-130.1,"z":-323.6,"mx":273,"my":854},{"t":45,"x":-123.4,"z":-316.9,"mx":280.5,"my":846.4},{"t":50,"x":-112.2,"z":-312.4,"mx":293.3,"my":841.3},{"t":55,"x":-91.1,"z":-325.2,"mx":317.3,"my":855.8},{"t":60,"x":-70,"z":-337.9,"mx":341.4,"my":870.3},{"t":65,"x":-60.2,"z":-318.1,"mx":352.4,"my":847.7},{"t":70,"x":-43.3,"z":-300.8,"mx":371.7,"my":828},{"t":75,"x":-23.6,"z":-293.7,"mx":394.2,"my":820},{"t":81,"x":-1,"z":-299.9,"mx":419.9,"my":827},{"t":86,"x":21.2,"z":-299.9,"mx":445.1,"my":827.1},{"t":91,"x":45.7,"z":-298.7,"mx":472.9,"my":825.7},{"t":96,"x":67.1,"z":-294.9,"mx":497.4,"my":821.4},{"t":101,"x":89.9,"z":-287.7,"mx":523.3,"my":813.2},{"t":106,"x":91.7,"z":-284.2,"mx":525.3,"my":809.2},{"t":111,"x":87.1,"z":-293,"mx":520.1,"my":819.2},{"t":116,"x":96.5,"z":-308.7,"mx":530.8,"my":837},{"t":121,"x":85.2,"z":-294.3,"mx":518,"my":820.7},{"t":126,"x":90.8,"z":-287.2,"mx":524.3,"my":812.6},{"t":131,"x":93.6,"z":-283.7,"mx":527.5,"my":808.6},{"t":136,"x":85.8,"z":-284.7,"mx":518.6,"my":809.8},{"t":141,"x":93.8,"z":-305,"mx":527.7,"my":832.9},{"t":146,"x":90.4,"z":-303.3,"mx":523.8,"my":830.9},{"t":151,"x":87.1,"z":-292.8,"mx":520.1,"my":819},{"t":156,"x":86.3,"z":-278.1,"mx":519.2,"my":802.3},{"t":161,"x":82.7,"z":-274.1,"mx":515.1,"my":797.7},{"t":166,"x":90.7,"z":-274.2,"mx":524.2,"my":797.8},{"t":171,"x":109,"z":-275.8,"mx":545,"my":799.7},{"t":186,"x":102.8,"z":-273.3,"mx":537.9,"my":796.7}]},{"playerId":"1448","isBot":true,"label":"Bot 1448","firstT":5,"lastT":282,"points":[{"t":5,"x":-171.2,"z":319.2,"mx":226.2,"my":122.7},{"t":10,"x":-161.2,"z":299.4,"mx":237.6,"my":145.1},{"t":15,"x":-147.1,"z":285.2,"mx":253.6,"my":161.3},{"t":20,"x":-139,"z":271.4,"mx":262.8,"my":177.1},{"t":25,"x":-125.3,"z":255.7,"mx":278.4,"my":194.9},{"t":30,"x":-121.8,"z":243.5,"mx":282.4,"my":208.7},{"t":35,"x":-125.6,"z":219.4,"mx":278.1,"my":236.2},{"t":40,"x":-131,"z":195.7,"mx":271.9,"my":263.1},{"t":45,"x":-131.8,"z":182.2,"mx":271.1,"my":278.5},{"t":50,"x":-119.2,"z":188.6,"mx":285.3,"my":271.2},{"t":55,"x":-136.3,"z":179.4,"mx":265.8,"my":281.8},{"t":60,"x":-121.8,"z":187.7,"mx":282.4,"my":272.3},{"t":65,"x":-99.1,"z":194.4,"mx":308.2,"my":264.7},{"t":70,"x":-92.4,"z":183.2,"mx":315.8,"my":277.4},{"t":75,"x":-111.4,"z":170.1,"mx":294.3,"my":292.3},{"t":81,"x":-111.8,"z":148,"mx":293.8,"my":317.5},{"t":86,"x":-112.3,"z":168,"mx":293.3,"my":294.6},{"t":91,"x":-114.3,"z":163.9,"mx":291,"my":299.4},{"t":96,"x":-103,"z":176.5,"mx":303.8,"my":285},{"t":101,"x":-89.6,"z":191.2,"mx":319,"my":268.3},{"t":106,"x":-106.5,"z":205.7,"mx":299.8,"my":251.8},{"t":111,"x":-116.9,"z":226.6,"mx":288,"my":228},{"t":116,"x":-115.3,"z":216.8,"mx":289.8,"my":239.1},{"t":121,"x":-105.4,"z":196.8,"mx":301,"my":261.9},{"t":126,"x":-83.8,"z":195.7,"mx":325.6,"my":263.2},{"t":131,"x":-61.1,"z":191.1,"mx":351.5,"my":268.4},{"t":141,"x":-86.5,"z":195.5,"mx":322.5,"my":263.3},{"t":146,"x":-109.2,"z":192.4,"mx":296.7,"my":266.9},{"t":151,"x":-131.1,"z":182.6,"mx":271.8,"my":278.1},{"t":156,"x":-138.5,"z":188.1,"mx":263.5,"my":271.9},{"t":161,"x":-134.6,"z":211.3,"mx":267.9,"my":245.4},{"t":166,"x":-131,"z":232.5,"mx":272,"my":221.3},{"t":171,"x":-139.5,"z":254.3,"mx":262.3,"my":196.5},{"t":176,"x":-145.2,"z":266.3,"mx":255.8,"my":182.8},{"t":181,"x":-142.3,"z":241.9,"mx":259,"my":210.6},{"t":186,"x":-139.6,"z":218.8,"mx":262.1,"my":236.9},{"t":191,"x":-128.5,"z":198.7,"mx":274.7,"my":259.8},{"t":196,"x":-110,"z":192.5,"mx":295.8,"my":266.8},{"t":201,"x":-91.8,"z":193.2,"mx":316.5,"my":266},{"t":206,"x":-100.4,"z":178.3,"mx":306.7,"my":283},{"t":211,"x":-109.2,"z":171.6,"mx":296.7,"my":290.6},{"t":216,"x":-109.3,"z":152.4,"mx":296.6,"my":312.4},{"t":221,"x":-104.6,"z":142.8,"mx":301.9,"my":323.4},{"t":226,"x":-90.1,"z":126.5,"mx":318.4,"my":341.9},{"t":231,"x":-77.6,"z":109.9,"mx":332.7,"my":360.8},{"t":236,"x":-69.5,"z":98.4,"mx":341.9,"my":373.8},{"t":241,"x":-55.6,"z":83.4,"mx":357.7,"my":390.9},{"t":246,"x":-53.2,"z":63.1,"mx":360.4,"my":414},{"t":251,"x":-41.1,"z":48.4,"mx":374.2,"my":430.8},{"t":257,"x":-26.3,"z":39.4,"mx":391,"my":441},{"t":262,"x":-20.6,"z":34.3,"mx":397.5,"my":446.8},{"t":267,"x":-11,"z":23.7,"mx":408.4,"my":458.9},{"t":272,"x":1.7,"z":11,"mx":422.9,"my":473.3},{"t":277,"x":5.6,"z":-12.7,"mx":427.3,"my":500.3},{"t":282,"x":25.4,"z":-14.4,"mx":449.9,"my":502.2}]},{"playerId":"1452","isBot":true,"label":"Bot 1452","firstT":5,"lastT":191,"points":[{"t":5,"x":-137.6,"z":-174.6,"mx":264.4,"my":684.5},{"t":10,"x":-125.8,"z":-170.5,"mx":277.8,"my":679.8},{"t":15,"x":-105.1,"z":-170,"mx":301.4,"my":679.2},{"t":20,"x":-100.2,"z":-163.8,"mx":307,"my":672.2},{"t":25,"x":-105.2,"z":-149.5,"mx":301.3,"my":656},{"t":30,"x":-101.8,"z":-133,"mx":305.1,"my":637.1},{"t":35,"x":-86.2,"z":-127.9,"mx":322.9,"my":631.4},{"t":40,"x":-79,"z":-111,"mx":331.1,"my":612.2},{"t":45,"x":-90.8,"z":-95.1,"mx":317.7,"my":594},{"t":50,"x":-104.1,"z":-88.2,"mx":302.5,"my":586.2},{"t":55,"x":-104.4,"z":-112.3,"mx":302.2,"my":613.6},{"t":60,"x":-109,"z":-133.7,"mx":296.9,"my":638},{"t":65,"x":-132.2,"z":-125.8,"mx":270.5,"my":629},{"t":70,"x":-154.9,"z":-117.4,"mx":244.7,"my":619.4},{"t":75,"x":-162.7,"z":-112.5,"mx":235.8,"my":613.8},{"t":81,"x":-155.7,"z":-135.5,"mx":243.8,"my":640},{"t":86,"x":-153.2,"z":-158.3,"mx":246.7,"my":665.9},{"t":91,"x":-136.5,"z":-169.9,"mx":265.7,"my":679.1},{"t":96,"x":-116.1,"z":-170.2,"mx":288.9,"my":679.5},{"t":101,"x":-99.4,"z":-169.8,"mx":307.8,"my":679.1},{"t":106,"x":-89,"z":-164.5,"mx":319.7,"my":673},{"t":111,"x":-74.5,"z":-154.8,"mx":336.3,"my":662},{"t":116,"x":-57.9,"z":-143.3,"mx":355.1,"my":648.9},{"t":121,"x":-38.9,"z":-128.6,"mx":376.7,"my":632.1},{"t":126,"x":-26.9,"z":-109.4,"mx":390.4,"my":610.3},{"t":131,"x":-15.5,"z":-102.8,"mx":403.4,"my":602.8},{"t":136,"x":1.4,"z":-97.2,"mx":422.5,"my":596.5},{"t":141,"x":-3.2,"z":-112.3,"mx":417.3,"my":613.6},{"t":146,"x":-5.4,"z":-135.6,"mx":414.9,"my":640.1},{"t":151,"x":-0.8,"z":-127.1,"mx":420.1,"my":630.5},{"t":156,"x":-9,"z":-104.4,"mx":410.7,"my":604.6},{"t":161,"x":-4.4,"z":-93.5,"mx":416,"my":592.2},{"t":166,"x":4,"z":-96.4,"mx":425.5,"my":595.5},{"t":171,"x":0.5,"z":-107.3,"mx":421.6,"my":607.9},{"t":176,"x":-2,"z":-99.3,"mx":418.7,"my":598.8},{"t":181,"x":4.6,"z":-78.7,"mx":426.2,"my":575.4},{"t":186,"x":15.4,"z":-57.3,"mx":438.5,"my":551.1},{"t":191,"x":28.5,"z":-39.6,"mx":453.4,"my":530.9}]},{"playerId":"1456","isBot":true,"label":"Bot 1456","firstT":5,"lastT":216,"points":[{"t":5,"x":-310.4,"z":15.5,"mx":67.9,"my":468.2},{"t":10,"x":-302.2,"z":19.9,"mx":77.1,"my":463.2},{"t":15,"x":-287.6,"z":39.4,"mx":93.7,"my":441},{"t":20,"x":-287.8,"z":42.2,"mx":93.5,"my":437.9},{"t":25,"x":-304.1,"z":29.1,"mx":75,"my":452.7},{"t":30,"x":-295,"z":32.1,"mx":85.3,"my":449.4},{"t":35,"x":-285.5,"z":53,"mx":96.2,"my":425.5},{"t":40,"x":-280.1,"z":64.5,"mx":102.3,"my":412.5},{"t":45,"x":-262.8,"z":48.3,"mx":122,"my":430.9},{"t":50,"x":-244.9,"z":36.3,"mx":142.4,"my":444.5},{"t":55,"x":-220.6,"z":38,"mx":170,"my":442.7},{"t":60,"x":-198.6,"z":41.8,"mx":195.1,"my":438.2},{"t":65,"x":-182.5,"z":54.8,"mx":213.4,"my":423.5},{"t":70,"x":-161.6,"z":57.9,"mx":237.1,"my":420},{"t":75,"x":-138.8,"z":60.8,"mx":263,"my":416.7},{"t":81,"x":-114.6,"z":65.3,"mx":290.6,"my":411.5},{"t":86,"x":-135.1,"z":60.9,"mx":267.3,"my":416.6},{"t":91,"x":-159,"z":55.8,"mx":240.1,"my":422.3},{"t":96,"x":-181.2,"z":45.4,"mx":214.8,"my":434.2},{"t":101,"x":-197.5,"z":29.7,"mx":196.2,"my":452},{"t":106,"x":-184.1,"z":20.9,"mx":211.5,"my":462},{"t":111,"x":-160.3,"z":15.2,"mx":238.6,"my":468.6},{"t":116,"x":-138.9,"z":10,"mx":262.9,"my":474.5},{"t":121,"x":-128.1,"z":8.6,"mx":275.3,"my":476},{"t":126,"x":-118.9,"z":19.9,"mx":285.7,"my":463.1},{"t":131,"x":-119.4,"z":30.1,"mx":285.1,"my":451.6},{"t":136,"x":-125.5,"z":42.1,"mx":278.2,"my":438},{"t":141,"x":-108.1,"z":42.5,"mx":297.9,"my":437.5},{"t":146,"x":-85.9,"z":53,"mx":323.2,"my":425.5},{"t":151,"x":-76.1,"z":41.4,"mx":334.3,"my":438.7},{"t":156,"x":-87.3,"z":47.9,"mx":321.7,"my":431.3},{"t":161,"x":-76.5,"z":41.8,"mx":334,"my":438.2},{"t":166,"x":-68.1,"z":24.3,"mx":343.5,"my":458.2},{"t":171,"x":-71.1,"z":3.3,"mx":340.1,"my":482.1},{"t":176,"x":-74.9,"z":-2.4,"mx":335.8,"my":488.6},{"t":181,"x":-68.1,"z":0.1,"mx":343.5,"my":485.7},{"t":186,"x":-76.3,"z":-15.4,"mx":334.1,"my":503.4},{"t":196,"x":-71.9,"z":-26.1,"mx":339.2,"my":515.5},{"t":201,"x":-77,"z":-25.7,"mx":333.4,"my":515},{"t":206,"x":-82.5,"z":-48.6,"mx":327.1,"my":541.1},{"t":211,"x":-87.1,"z":-38.4,"mx":321.9,"my":529.5},{"t":216,"x":-99.5,"z":-27.9,"mx":307.7,"my":517.6}]}],"events":[{"id":"e0","event":"Loot","category":"loot","t":36,"x":186.3,"z":-82.9,"mx":633,"my":580.1,"playerId":"2980f2c1-1207-428d-af58-cc62498e6dbb","isBot":false},{"id":"e1","event":"BotKill","category":"kill","t":42,"x":-128.4,"z":-320.2,"mx":274.9,"my":850.2,"playerId":"1444","isBot":true},{"id":"e2","event":"Loot","category":"loot","t":65,"x":158.8,"z":-74.6,"mx":601.6,"my":570.7,"playerId":"2980f2c1-1207-428d-af58-cc62498e6dbb","isBot":false},{"id":"e3","event":"Loot","category":"loot","t":72,"x":153,"z":-73.8,"mx":595,"my":569.8,"playerId":"2980f2c1-1207-428d-af58-cc62498e6dbb","isBot":false},{"id":"e4","event":"Loot","category":"loot","t":78,"x":150.1,"z":-78.6,"mx":591.7,"my":575.3,"playerId":"2980f2c1-1207-428d-af58-cc62498e6dbb","isBot":false},{"id":"e5","event":"Loot","category":"loot","t":82,"x":146.9,"z":-78.8,"mx":588.1,"my":575.5,"playerId":"2980f2c1-1207-428d-af58-cc62498e6dbb","isBot":false},{"id":"e6","event":"Loot","category":"loot","t":97,"x":150.5,"z":-89.9,"mx":592.2,"my":588.1,"playerId":"2980f2c1-1207-428d-af58-cc62498e6dbb","isBot":false},{"id":"e7","event":"Loot","category":"loot","t":99,"x":151.4,"z":-91.6,"mx":593.2,"my":590,"playerId":"2980f2c1-1207-428d-af58-cc62498e6dbb","isBot":false},{"id":"e8","event":"BotKilled","category":"death","t":103,"x":-6.6,"z":-2.6,"mx":413.4,"my":488.8,"playerId":"1440","isBot":true},{"id":"e9","event":"Loot","category":"loot","t":161,"x":199.7,"z":-254.2,"mx":648.2,"my":775,"playerId":"2980f2c1-1207-428d-af58-cc62498e6dbb","isBot":false},{"id":"e10","event":"BotKill","category":"kill","t":171,"x":-71.3,"z":2.9,"mx":339.8,"my":482.5,"playerId":"1456","isBot":true},{"id":"e11","event":"Loot","category":"loot","t":190,"x":201.2,"z":-271.9,"mx":649.9,"my":795.2,"playerId":"2980f2c1-1207-428d-af58-cc62498e6dbb","isBot":false},{"id":"e12","event":"BotKilled","category":"death","t":196,"x":26.9,"z":-29.2,"mx":451.6,"my":519,"playerId":"1452","isBot":true},{"id":"e13","event":"BotKilled","category":"death","t":217,"x":-96.8,"z":-27.9,"mx":310.8,"my":517.5,"playerId":"1456","isBot":true},{"id":"e14","event":"Loot","category":"loot","t":231,"x":175.5,"z":-300.7,"mx":620.6,"my":827.9,"playerId":"2980f2c1-1207-428d-af58-cc62498e6dbb","isBot":false},{"id":"e15","event":"Loot","category":"loot","t":238,"x":166.2,"z":-288.5,"mx":610.1,"my":814.1,"playerId":"2980f2c1-1207-428d-af58-cc62498e6dbb","isBot":false},{"id":"e16","event":"Loot","category":"loot","t":240,"x":164.2,"z":-288.2,"mx":607.8,"my":813.7,"playerId":"2980f2c1-1207-428d-af58-cc62498e6dbb","isBot":false},{"id":"e17","event":"BotKilled","category":"death","t":284,"x":34.1,"z":-18.7,"mx":459.8,"my":507.1,"playerId":"1448","isBot":true},{"id":"e18","event":"BotKill","category":"kill","t":296,"x":-7,"z":-48.9,"mx":413,"my":541.5,"playerId":"1436","isBot":true},{"id":"e19","event":"Loot","category":"loot","t":340,"x":-54.5,"z":-354.4,"mx":359,"my":889.1,"playerId":"2980f2c1-1207-428d-af58-cc62498e6dbb","isBot":false},{"id":"e20","event":"Loot","category":"loot","t":348,"x":-53,"z":-357.3,"mx":360.7,"my":892.3,"playerId":"2980f2c1-1207-428d-af58-cc62498e6dbb","isBot":false},{"id":"e21","event":"Loot","category":"loot","t":350,"x":-52.9,"z":-358.6,"mx":360.8,"my":893.8,"playerId":"2980f2c1-1207-428d-af58-cc62498e6dbb","isBot":false},{"id":"e22","event":"BotKilled","category":"death","t":360,"x":3.8,"z":-11.2,"mx":425.3,"my":498.6,"playerId":"1436","isBot":true},{"id":"e23","event":"Loot","category":"loot","t":388,"x":0,"z":-277.8,"mx":420.9,"my":802,"playerId":"2980f2c1-1207-428d-af58-cc62498e6dbb","isBot":false},{"id":"e24","event":"Loot","category":"loot","t":390,"x":-2.7,"z":-281.3,"mx":417.9,"my":805.9,"playerId":"2980f2c1-1207-428d-af58-cc62498e6dbb","isBot":false},{"id":"e25","event":"Loot","category":"loot","t":396,"x":-5.1,"z":-286.1,"mx":415.1,"my":811.4,"playerId":"2980f2c1-1207-428d-af58-cc62498e6dbb","isBot":false},{"id":"e26","event":"Loot","category":"loot","t":411,"x":-17.6,"z":-281.4,"mx":400.9,"my":806,"playerId":"2980f2c1-1207-428d-af58-cc62498e6dbb","isBot":false}]}