{"matchId":"e12352da-d705-4e3d-8abe-422b515087ce.nakama-0","mapId":"AmbroseValley","date":"2026-02-11","startTime":1770788985000,"endTime":1770789559000,"durationSeconds":574,"players":[{"playerId":"eccd1dc0-1795-4f57-97c5-fcfa0282eec1","isBot":false,"label":"Human eccd1d","firstT":0,"lastT":574,"points":[{"t":0,"x":-170.4,"z":338,"mx":227.1,"my":101.3},{"t":126,"x":-164.7,"z":326.7,"mx":233.5,"my":114.1},{"t":131,"x":-162.6,"z":315.2,"mx":236,"my":127.2},{"t":136,"x":-173.7,"z":313.2,"mx":223.4,"my":129.5},{"t":141,"x":-161.9,"z":300.7,"mx":236.8,"my":143.7},{"t":146,"x":-156.7,"z":297.8,"mx":242.7,"my":147},{"t":156,"x":-160.8,"z":296.9,"mx":238.1,"my":148},{"t":161,"x":-159.6,"z":298.6,"mx":239.4,"my":146},{"t":166,"x":-153.3,"z":302.7,"mx":246.5,"my":141.4},{"t":176,"x":-146,"z":305.4,"mx":254.9,"my":138.3},{"t":181,"x":-138,"z":291.5,"mx":264,"my":154.2},{"t":186,"x":-138.3,"z":277,"mx":263.6,"my":170.7},{"t":191,"x":-124.3,"z":254.7,"mx":279.6,"my":196.1},{"t":196,"x":-126,"z":249.3,"mx":277.7,"my":202.2},{"t":201,"x":-125.3,"z":250.5,"mx":278.4,"my":200.8},{"t":207,"x":-114.6,"z":250.2,"mx":290.6,"my":201.2},{"t":212,"x":-114.7,"z":246.9,"mx":290.5,"my":204.9},{"t":433,"x":-111.8,"z":240.6,"mx":293.8,"my":212.1},{"t":438,"x":-112.4,"z":238.6,"mx":293.1,"my":214.4},{"t":448,"x":-114.3,"z":234.6,"mx":290.9,"my":218.9},{"t":453,"x":-122.6,"z":217.5,"mx":281.4,"my":238.4},{"t":458,"x":-129.2,"z":200.9,"mx":273.9,"my":257.3},{"t":463,"x":-136.4,"z":183.9,"mx":265.8,"my":276.6},{"t":468,"x":-136.8,"z":178.3,"mx":265.4,"my":283},{"t":473,"x":-136.8,"z":171,"mx":265.3,"my":291.3},{"t":488,"x":-143,"z":175,"mx":258.3,"my":286.7},{"t":493,"x":-159.9,"z":169.6,"mx":239,"my":292.8},{"t":498,"x":-177.2,"z":163.9,"mx":219.4,"my":299.3},{"t":503,"x":-190.4,"z":151.5,"mx":204.3,"my":313.5},{"t":508,"x":-194.6,"z":134.2,"mx":199.6,"my":333.1},{"t":513,"x":-187,"z":122.6,"mx":208.2,"my":346.3},{"t":518,"x":-175.8,"z":109.8,"mx":221,"my":360.9},{"t":523,"x":-158.3,"z":108.3,"mx":240.8,"my":362.6},{"t":528,"x":-140,"z":100,"mx":261.7,"my":372},{"t":533,"x":-125.6,"z":98.8,"mx":278,"my":373.4},{"t":538,"x":-117.4,"z":86.8,"mx":287.4,"my":387.1},{"t":543,"x":-107.8,"z":79.5,"mx":298.3,"my":395.4},{"t":548,"x":-98.2,"z":73.4,"mx":309.3,"my":402.3},{"t":553,"x":-83.5,"z":74.8,"mx":326,"my":400.7},{"t":559,"x":-69,"z":66.3,"mx":342.5,"my":410.4},{"t":564,"x":-74.9,"z":67.5,"mx":335.7,"my":409.1},{"t":569,"x":-85.9,"z":71.6,"mx":323.3,"my":404.4},{"t":574,"x":-85.5,"z":67.9,"mx":323.7,"my":408.5}]}],"events":[{"id":"e0","event":"Loot","category":"loot","t":135,"x":-175.4,"z":313.7,"mx":221.5,"my":128.9,"playerId":"eccd1dc0-1795-4f57-97c5-fcfa0282eec1","isBot":false},{"id":"e1","event":"Loot","category":"loot","t":149,"x":-156.8,"z":298.2,"mx":242.5,"my":146.6,"playerId":"eccd1dc0-1795-4f57-97c5-fcfa0282eec1","isBot":false},{"id":"e2","event":"Loot","category":"loot","t":156,"x":-160.8,"z":296.9,"mx":238.1,"my":148,"playerId":"eccd1dc0-1795-4f57-97c5-fcfa0282eec1","isBot":false},{"id":"e3","event":"Loot","category":"loot","t":158,"x":-160.8,"z":296.9,"mx":238.1,"my":148,"playerId":"eccd1dc0-1795-4f57-97c5-fcfa0282eec1","isBot":false},{"id":"e4","event":"Loot","category":"loot","t":165,"x":-153.3,"z":302.7,"mx":246.5,"my":141.4,"playerId":"eccd1dc0-1795-4f57-97c5-fcfa0282eec1","isBot":false},{"id":"e5","event":"Loot","category":"loot","t":166,"x":-153.3,"z":302.7,"mx":246.5,"my":141.4,"playerId":"eccd1dc0-1795-4f57-97c5-fcfa0282eec1","isBot":false},{"id":"e6","event":"Loot","category":"loot","t":200,"x":-126,"z":249.3,"mx":277.7,"my":202.2,"playerId":"eccd1dc0-1795-4f57-97c5-fcfa0282eec1","isBot":false},{"id":"e7","event":"Loot","category":"loot","t":466,"x":-136.2,"z":182.9,"mx":266,"my":277.8,"playerId":"eccd1dc0-1795-4f57-97c5-fcfa0282eec1","isBot":false},{"id":"e8","event":"Loot","category":"loot","t":466,"x":-136.2,"z":182.9,"mx":266,"my":277.8,"playerId":"eccd1dc0-1795-4f57-97c5-fcfa0282eec1","isBot":false},{"id":"e9","event":"Loot","category":"loot","t":469,"x":-137.2,"z":175.4,"mx":264.8,"my":286.3,"playerId":"eccd1dc0-1795-4f57-97c5-fcfa0282eec1","isBot":false},{"id":"e10","event":"Loot","category":"loot","t":487,"x":-141.2,"z":175.3,"mx":260.4,"my":286.3,"playerId":"eccd1dc0-1795-4f57-97c5-fcfa0282eec1","isBot":false},{"id":"e11","event":"BotKilled","category":"death","t":570,"x":-85.7,"z":68,"mx":323.5,"my":408.5,"playerId":"eccd1dc0-1795-4f57-97c5-fcfa0282eec1","isBot":false}]}